README.rst
setup.py
libpymux/__init__.py
libpymux/input.py
libpymux/invalidate.py
libpymux/layout.py
libpymux/log.py
libpymux/panes.py
libpymux/pexpect_utils.py
libpymux/renderer.py
libpymux/screen.py
libpymux/session.py
libpymux/statusbar.py
libpymux/std.py
libpymux/utils.py
libpymux/window.py
libpymux.egg-info/PKG-INFO
libpymux.egg-info/SOURCES.txt
libpymux.egg-info/dependency_links.txt
libpymux.egg-info/requires.txt
libpymux.egg-info/top_level.txt