Metadata-Version: 1.0
Name: libpymux
Version: 0.1
Summary: Python terminal multiplexer (Pure Python tmux clone)
Home-page: https://github.com/jonathanslenders/libpymux
Author: Jonathan Slenders
Author-email: UNKNOWN
License: LICENSE.txt
Platform: UNKNOWN
